hybridbackend_cpu_legacy.libs/libcrypto-d4247593.so.1.1
hybridbackend_cpu_legacy.libs/libunistring-63cdc3c9.so.0.1.2
hybridbackend_cpu_legacy.libs/libldap_r-2-dd5ad718.4.so.2.10.7
hybridbackend_cpu_legacy.libs/libidn-fd653b64.so.11.6.16
hybridbackend_cpu_legacy.libs/libnghttp2-bc81ecbc.so.14.12.3
hybridbackend_cpu_legacy.libs/libssl-c0504cd1.so.1.0.2
hybridbackend_cpu_legacy.libs/libkrb5support-86ac49ad.so.0.1
hybridbackend_cpu_legacy.libs/librtmp-811a3a2f.so.1
hybridbackend_cpu_legacy.libs/libgcrypt-0005395c.so.20.1.6
hybridbackend_cpu_legacy.libs/libk5crypto-93afd15e.so.3.1
hybridbackend_cpu_legacy.libs/libgmp-742f5e74.so.10.3.2
hybridbackend_cpu_legacy.libs/libcrypto-eaeb3723.so.1.0.2
hybridbackend_cpu_legacy.libs/libgpg-error-24781f22.so.0.21.0
hybridbackend_cpu_legacy.libs/libgnutls-1ec2cd13.so.30.13.1
hybridbackend_cpu_legacy.libs/libcom_err-b4bd5c72.so.2.1
hybridbackend_cpu_legacy.libs/libp11-kit-d06ac4a7.so.0.2.0
hybridbackend_cpu_legacy.libs/libpsl-689f63ce.so.5.1.1
hybridbackend_cpu_legacy.libs/libssh2-f6c6529c.so.1.0.1
hybridbackend_cpu_legacy.libs/libgssapi_krb5-e296a08d.so.2.2
hybridbackend_cpu_legacy.libs/libtasn1-44938221.so.6.5.3
hybridbackend_cpu_legacy.libs/libssl-e86845de.so.1.1
hybridbackend_cpu_legacy.libs/libcurl-5de385f6.so.4.4.0
hybridbackend_cpu_legacy.libs/libnettle-2482db45.so.6.3
hybridbackend_cpu_legacy.libs/libkeyutils-46318358.so.1.5
hybridbackend_cpu_legacy.libs/libffi-1c6807d3.so.6.0.4
hybridbackend_cpu_legacy.libs/libhogweed-9d325a8d.so.4.3
hybridbackend_cpu_legacy.libs/libkrb5-061fe33b.so.3.3
hybridbackend_cpu_legacy.libs/liblber-2-8665b4a9.4.so.2.10.7
hybridbackend_cpu_legacy.libs/libidn2-405cb51a.so.0.1.4
hybridbackend_cpu_legacy.libs/libsasl2-4427c928.so.2.0.25
hybridbackend/libhybridbackend.so
hybridbackend/__init__.py
hybridbackend/tools/dataset_mock.py
hybridbackend/tools/dataset_benchmark.py
hybridbackend/tools/__init__.py
hybridbackend/torch/__init__.py
hybridbackend_cpu_legacy-0.5.4.post1.dist-info/NOTICE
hybridbackend_cpu_legacy-0.5.4.post1.dist-info/RECORD
hybridbackend_cpu_legacy-0.5.4.post1.dist-info/WHEEL
hybridbackend_cpu_legacy-0.5.4.post1.dist-info/top_level.txt
hybridbackend_cpu_legacy-0.5.4.post1.dist-info/METADATA
hybridbackend_cpu_legacy-0.5.4.post1.dist-info/LICENSE
